kubehelper/__init__.py
kubehelper/yamlBuilder.py
kubehelper-0.1.0.dist-info/WHEEL
kubehelper-0.1.0.dist-info/METADATA
kubehelper-0.1.0.dist-info/RECORD
